iridiummodem/__init__.py
iridiummodem/modem.py
python_iridium_modem-0.1.1.data/scripts/print-geolocation.py
python_iridium_modem-0.1.1.dist-info/AUTHORS
python_iridium_modem-0.1.1.dist-info/COPYING
python_iridium_modem-0.1.1.dist-info/METADATA
python_iridium_modem-0.1.1.dist-info/WHEEL
python_iridium_modem-0.1.1.dist-info/top_level.txt
python_iridium_modem-0.1.1.dist-info/RECORD
