Metadata-Version: 2.1
Name: python-iridium-modem
Version: 0.1.1
Summary: Iridium phone library
Home-page: https://github.com/tdolby/python-iridium-modem
Author: Trevor Dolby
Author-email: github@tdolby.demon.co.uk
License: LGPLv3+
Keywords: iridium satellite phone modem
Platform: UNKNOWN
Classifier: Development Status :: 3 - Alpha
Classifier: Intended Audience :: Developers
Classifier: Topic :: Software Development :: Build Tools
Classifier: License :: OSI Approved :: GNU Lesser General Public License v3 or later (LGPLv3+)
Classifier: Programming Language :: Python :: 3
Classifier: Programming Language :: Python :: 3.4
Classifier: Programming Language :: Python :: 3.5
Classifier: Programming Language :: Python :: 3.6
Classifier: Programming Language :: Python :: 3.7
Classifier: Programming Language :: Python :: 3.8
Requires-Dist: pyserial
Requires-Dist: python-dateutil
Requires-Dist: python-gsmmodem-new
Provides-Extra: dev
Requires-Dist: check-manifest ; extra == 'dev'
Provides-Extra: test
Requires-Dist: coverage ; extra == 'test'
